[
  {
    "key": "text_13_text",
    "text": "치아와 턱의 비정상적인 위치를 교정하여",
    "location": "line:1019, tag:text",
    "context": "text",
    "translated": "치아와 턱의 비정상적인 위치를 교정하여"
  },
  {
    "key": "text_14_text",
    "text": "미소와 턱의 기능을 향상시키는 치료과정입니다.",
    "location": "line:1020, tag:text",
    "context": "text",
    "translated": "미소와 턱의 기능을 향상시키는 치료과정입니다."
  },
  {
    "key": "text_15_text",
    "text": "치아의 이상적인 위치와 상태를 재조정하여",
    "location": "line:1023, tag:text",
    "context": "text",
    "translated": "치아의 이상적인 위치와 상태를 재조정하여"
  },
  {
    "key": "text_16_text",
    "text": "아름다운 스마일 라인과 건강한 구강을 선사합니다.",
    "location": "line:1024, tag:text",
    "context": "text",
    "translated": "아름다운 스마일 라인과 건강한 구강을 선사합니다."
  },
  {
    "key": "text_19_text",
    "text": "치아교정은 치아와 턱의 비정상적인 위치나 교합 문제를 전문 교정 장치를 이용하여 바르게 교정하는 치료과정입니다. 턱과 치아의 위치를 조정하여 교합과 치아의 기능을 안정시키고, 변화된 턱의 길이와 위치를 조절하여 턱과 안면 근육의 균형을 맞출 수 있습니다. 아름다운 스마일 라인과 함께 건강한 구강 기능을 되찾을 수 있습니다.",
    "location": "line:1084, tag:text",
    "context": "text",
    "translated": "牙齒矯正은 치아와 턱의 비정상적인 위치나 교합 문제를 전문 교정 장치를 이용하여 바르게 교정하는 치료과정입니다. 턱과 치아의 위치를 조정하여 교합과 치아의 기능을 안정시키고, 변화된 턱의 길이와 위치를 조절하여 턱과 안면 근육의 균형을 맞출 수 있습니다. 아름다운 스마일 라인과 함께 건강한 구강 기능을 되찾을 수 있습니다."
  },
  {
    "key": "text_33_text",
    "text": "선수술 교정은 기존의 '교정 → 수술' 순서를 역전시켜, 턱수술을 먼저 시행한 뒤 교정 치료를 진행하는 방법입니다. 수술을 통해 골격적 부조화를 먼저 해결하므로 외모 개선이 빠르게 이루어지며, 비정상적인 골격이 정상 골격으로 바뀌면서 심미적 만족감을 조기에 얻을 수 있습니다.",
    "location": "line:1142, tag:text",
    "context": "text",
    "translated": "術前矯正은 기존의 '교정 → 수술' 순서를 역전시켜, 턱수술을 먼저 시행한 뒤 교정 치료를 진행하는 방법입니다. 수술을 통해 골격적 부조화를 먼저 해결하므로 외모 개선이 빠르게 이루어지며, 비정상적인 골격이 정상 골격으로 바뀌면서 심미적 만족감을 조기에 얻을 수 있습니다."
  },
  {
    "key": "text_34_text",
    "text": "수술 후 변화된 턱과 치아의 위치를 정밀하게 재조정하여 교합과 치아의 기능을 안정시키고 회복시키는 것이 핵심 목적이며, 전통적인 교정-수술 방식 대비 전체 치료 기간을 단축할 수 있는 장점이 있습니다.",
    "location": "line:1145, tag:text",
    "context": "text",
    "translated": "수술 후 변화된 턱과 치아의 위치를 정밀하게 재조정하여 교합과 치아의 기능을 안정시키고 회복시키는 것이 핵심 목적이며, 전통적인 교정-수술 방식 대비 전체 치료 기간을 단축할 수 있는 장점이 있습니다."
  },
  {
    "key": "text_35_span",
    "text": "Surgery First 선수술 우선",
    "location": "line:1149, tag:span",
    "context": "text",
    "translated": "Surgery First 선수술 우선"
  },
  {
    "key": "text_38_p",
    "text": "3D CT와 구강 스캔을 통해 골격 및 치아 상태를 정밀하게 분석하고, 환자의 얼굴 형태와 교합 상태를 종합적으로 평가하여 최적의 수술 계획을 수립합니다.",
    "location": "line:1164, tag:p",
    "context": "text",
    "translated": "3D CT와 구강 스캔을 통해 골격 및 치아 상태를 정밀하게 분석하고, 환자의 얼굴 형태와 교합 상태를 종합적으로 평가하여 최적의 수술 계획을 수립합니다."
  },
  {
    "key": "text_40_p",
    "text": "골격적 부조화를 해결하고 심미적 개선의 기반을 마련하는 단계입니다. 수술을 통해 비정상적인 골격이 정상 위치로 이동하여 외모 개선이 빠르게 나타납니다.",
    "location": "line:1176, tag:p",
    "context": "text",
    "translated": "골격적 부조화를 해결하고 심미적 개선의 기반을 마련하는 단계입니다. 수술을 통해 비정상적인 골격이 정상 위치로 이동하여 외모 개선이 빠르게 나타납니다."
  }
]